command_saver/__init__.py
command_saver/constants.py
command_saver/cs.py
command_saver/run_me.py
command_saver/disposition/__init__.py
command_saver/errors/__init__.py
command_saver/errors/err.py
command_saver/errors/sql_err.py
command_saver/input_window/__init__.py
command_saver/input_window/input_window.py
command_saver/string_templates/__init__.py
command_saver/string_templates/error_str.py
command_saver/string_templates/logging_str.py
command_saver/string_templates/user_prompts.py
command_saver/table/__init__.py
command_saver/table/menu_options.py
command_saver/table/saved_commands.py
command_saver/table/user_data.py
command_saver/utils/__init__.py
command_saver/utils/default_database.py
command_saver/visual_design/__init__.py
command_saver/visual_design/formatter.py
command_saver/visual_design/view_contents.py
command_saver_terminal_program-2.2.2.data/scripts/cs.bat
command_saver_terminal_program-2.2.2.data/scripts/cs_script.sh
tests/__init__.py
tests/test_run_me.py
command_saver_terminal_program-2.2.2.dist-info/LICENSE
command_saver_terminal_program-2.2.2.dist-info/METADATA
command_saver_terminal_program-2.2.2.dist-info/WHEEL
command_saver_terminal_program-2.2.2.dist-info/entry_points.txt
command_saver_terminal_program-2.2.2.dist-info/top_level.txt
command_saver_terminal_program-2.2.2.dist-info/RECORD
