Metadata-Version: 2.1
Name: command-saver-terminal-program
Version: 2.2.2
Summary: Simple terminal helper program to save long terminal commands. See git: https://github.com/Zzanetiite/CommandSaver
License-File: LICENSE
Requires-Dist: rich ==13.3.3
